setup.py
bin/xetracker
xetracker/__init__.py
xetracker.egg-info/PKG-INFO
xetracker.egg-info/SOURCES.txt
xetracker.egg-info/dependency_links.txt
xetracker.egg-info/requires.txt
xetracker.egg-info/top_level.txt
xetracker/fetchers/__init__.py
xetracker/fetchers/charlie.py
xetracker/model/__init__.py
xetracker/model/currency_conversion.py
xetracker/persistance/__init__.py
xetracker/persistance/currency_conversion_dao.py