Metadata-Version: 1.0
Name: xetracker
Version: 0.1.4
Summary: Track the rates of the foreign currency traders
Home-page: https://github.com/tasyrkin/xetracker
Author: tasyrkin
Author-email: tasyrkin@gmail.com
License: UNKNOWN
Platform: UNKNOWN
